flowquery/__init__.py
flowquery/__main__.py
flowquery/extensibility.py
flowquery/compute/__init__.py
flowquery/compute/runner.py
flowquery/graph/__init__.py
flowquery/graph/data.py
flowquery/graph/database.py
flowquery/graph/hops.py
flowquery/graph/node.py
flowquery/graph/node_data.py
flowquery/graph/node_reference.py
flowquery/graph/pattern.py
flowquery/graph/pattern_expression.py
flowquery/graph/patterns.py
flowquery/graph/physical_node.py
flowquery/graph/physical_relationship.py
flowquery/graph/relationship.py
flowquery/graph/relationship_data.py
flowquery/graph/relationship_match_collector.py
flowquery/graph/relationship_reference.py
flowquery/io/__init__.py
flowquery/io/command_line.py
flowquery/parsing/__init__.py
flowquery/parsing/alias.py
flowquery/parsing/alias_option.py
flowquery/parsing/ast_node.py
flowquery/parsing/base_parser.py
flowquery/parsing/context.py
flowquery/parsing/parser.py
flowquery/parsing/token_to_node.py
flowquery/parsing/components/__init__.py
flowquery/parsing/components/csv.py
flowquery/parsing/components/from_.py
flowquery/parsing/components/headers.py
flowquery/parsing/components/json.py
flowquery/parsing/components/null.py
flowquery/parsing/components/post.py
flowquery/parsing/components/text.py
flowquery/parsing/data_structures/__init__.py
flowquery/parsing/data_structures/associative_array.py
flowquery/parsing/data_structures/json_array.py
flowquery/parsing/data_structures/key_value_pair.py
flowquery/parsing/data_structures/lookup.py
flowquery/parsing/data_structures/range_lookup.py
flowquery/parsing/expressions/__init__.py
flowquery/parsing/expressions/boolean.py
flowquery/parsing/expressions/expression.py
flowquery/parsing/expressions/expression_map.py
flowquery/parsing/expressions/f_string.py
flowquery/parsing/expressions/identifier.py
flowquery/parsing/expressions/number.py
flowquery/parsing/expressions/operator.py
flowquery/parsing/expressions/reference.py
flowquery/parsing/expressions/string.py
flowquery-1.0.10.dist-info/METADATA
flowquery-1.0.10.dist-info/WHEEL
flowquery-1.0.10.dist-info/entry_points.txt
flowquery-1.0.10.dist-info/top_level.txt
flowquery-1.0.10.dist-info/RECORD
