Metadata-Version: 2.4
Name: flowquery
Version: 1.0.10
Summary: A declarative query language for data processing pipelines
Author: FlowQuery Contributors
License: MIT
Project-URL: Homepage, https://github.com/microsoft/FlowQuery/flowquery-py
Project-URL: Repository, https://github.com/microsoft/FlowQuery/flowquery-py
Project-URL: Documentation, https://github.com/microsoft/FlowQuery/flowquery-py#readme
Project-URL: Issues, https://github.com/microsoft/FlowQuery/issues
Keywords: query,data-processing,pipeline,declarative
Classifier: Development Status :: 4 - Beta
Classifier: Intended Audience :: Developers
Classifier: License :: OSI Approved :: MIT License
Classifier: Operating System :: OS Independent
Classifier: Programming Language :: Python :: 3
Classifier: Programming Language :: Python :: 3.10
Classifier: Programming Language :: Python :: 3.11
Classifier: Programming Language :: Python :: 3.12
Classifier: Topic :: Database :: Front-Ends
Classifier: Topic :: Software Development :: Libraries :: Python Modules
Requires-Python: >=3.10
Requires-Dist: aiohttp>=3.8.0
Provides-Extra: dev
Requires-Dist: pytest>=7.0.0; extra == "dev"
Requires-Dist: pytest-asyncio>=0.21.0; extra == "dev"
Requires-Dist: jupyter>=1.0.0; extra == "dev"
Requires-Dist: ipykernel>=6.0.0; extra == "dev"
Requires-Dist: nbstripout>=0.6.0; extra == "dev"
Requires-Dist: mypy>=1.0.0; extra == "dev"
Requires-Dist: ruff>=0.1.0; extra == "dev"
